testPackage/__init__.py
testPackage/data_analysis_functions.py
testPackage/mainFile.py
testhistpackage-0.1.dist-info/METADATA
testhistpackage-0.1.dist-info/WHEEL
testhistpackage-0.1.dist-info/top_level.txt
testhistpackage-0.1.dist-info/RECORD
