Metadata-Version: 2.1
Name: testhistpackage
Version: 0.1
Summary: tutorial
Home-page: UNKNOWN
Author: 
Author-email: 
License: MIT
Platform: UNKNOWN
Requires-Dist: pandas
Requires-Dist: numpy
Requires-Dist: scipy
Requires-Dist: mpl-finance
Requires-Dist: matplotlib
Requires-Dist: statsmodels
Requires-Dist: patsy
